diameter_synthesis/__init__.py
diameter_synthesis/build_diameters.py
diameter_synthesis/build_models.py
diameter_synthesis/cli.py
diameter_synthesis/distribution_fitting.py
diameter_synthesis/exception.py
diameter_synthesis/main.py
diameter_synthesis/morph_functions.py
diameter_synthesis/plotting.py
diameter_synthesis/simpler_diametrizer.py
diameter_synthesis/utils.py
diameter_synthesis/validators.py
diameter_synthesis/schemas/config.json
diameter_synthesis/schemas/model_params.json
diameter_synthesis-0.7.0.dist-info/AUTHORS.md
diameter_synthesis-0.7.0.dist-info/LICENSE.txt
diameter_synthesis-0.7.0.dist-info/METADATA
diameter_synthesis-0.7.0.dist-info/WHEEL
diameter_synthesis-0.7.0.dist-info/entry_points.txt
diameter_synthesis-0.7.0.dist-info/top_level.txt
diameter_synthesis-0.7.0.dist-info/RECORD
