Metadata-Version: 2.1
Name: diameter-synthesis
Version: 0.7.0
Summary: Diametrize cells.
Home-page: https://diameter-synthesis.readthedocs.io
Author: Blue Brain Project, EPFL
License: Apache License 2.0
Project-URL: Tracker, https://github.com/BlueBrain/diameter-synthesis/issues
Project-URL: Source, https://github.com/BlueBrain/diameter-synthesis
Classifier: Development Status :: 4 - Beta
Classifier: Intended Audience :: Science/Research
Classifier: License :: OSI Approved :: Apache Software License
Classifier: Programming Language :: Python
Classifier: Programming Language :: Python :: 3
Classifier: Programming Language :: Python :: 3.9
Classifier: Programming Language :: Python :: 3.10
Classifier: Programming Language :: Python :: 3.11
Classifier: Programming Language :: Python :: 3.12
Classifier: Topic :: Scientific/Engineering :: Bio-Informatics
Requires-Python: >=3.9
License-File: LICENSE.txt
License-File: AUTHORS.md
Requires-Dist: click >=7.0
Requires-Dist: jsonschema >=3
Requires-Dist: matplotlib >=3.4
Requires-Dist: morphio >=3.3.4
Requires-Dist: neurom <4.0,>=3.0
Requires-Dist: numpy >=1.23
Requires-Dist: pandas >=1.5
Requires-Dist: scipy >=1.6
Requires-Dist: tqdm >=4.50
Provides-Extra: docs
Requires-Dist: docutils <0.21 ; extra == 'docs'
Requires-Dist: m2r2 ; extra == 'docs'
Requires-Dist: sphinx ; extra == 'docs'
Requires-Dist: sphinx-bluebrain-theme ; extra == 'docs'
Requires-Dist: sphinx-jsonschema ; extra == 'docs'
Requires-Dist: sphinx-click ; extra == 'docs'
Provides-Extra: plot
Requires-Dist: seaborn >=0.13 ; extra == 'plot'
Provides-Extra: test
Requires-Dist: diff-pdf-visually >=1.7.0 ; extra == 'test'
Requires-Dist: decorator >=4 ; extra == 'test'
Requires-Dist: dictdiffer >=0.9 ; extra == 'test'
Requires-Dist: mock >=3 ; extra == 'test'
Requires-Dist: pytest >=6.1 ; extra == 'test'
Requires-Dist: pytest-click >=1.1 ; extra == 'test'
Requires-Dist: pytest-console-scripts >=1.4 ; extra == 'test'
Requires-Dist: pytest-cov >=4.1 ; extra == 'test'
Requires-Dist: pytest-html >=3.2 ; extra == 'test'
Requires-Dist: pytest-xdist >=2 ; extra == 'test'
